huaweicloudsdkram/__init__.py
huaweicloudsdkram/v1/__init__.py
huaweicloudsdkram/v1/ram_async_client.py
huaweicloudsdkram/v1/ram_client.py
huaweicloudsdkram/v1/model/__init__.py
huaweicloudsdkram/v1/model/accept_resource_share_invitation_request.py
huaweicloudsdkram/v1/model/accept_resource_share_invitation_response.py
huaweicloudsdkram/v1/model/associate_permission_req_body.py
huaweicloudsdkram/v1/model/associate_resource_share_permission_request.py
huaweicloudsdkram/v1/model/associate_resource_share_permission_response.py
huaweicloudsdkram/v1/model/associate_resource_share_request.py
huaweicloudsdkram/v1/model/associate_resource_share_response.py
huaweicloudsdkram/v1/model/associated_permission.py
huaweicloudsdkram/v1/model/batch_create_resource_share_tags_request.py
huaweicloudsdkram/v1/model/batch_create_resource_share_tags_response.py
huaweicloudsdkram/v1/model/batch_delete_resource_share_tags_request.py
huaweicloudsdkram/v1/model/batch_delete_resource_share_tags_response.py
huaweicloudsdkram/v1/model/create_resource_share_req_body.py
huaweicloudsdkram/v1/model/create_resource_share_request.py
huaweicloudsdkram/v1/model/create_resource_share_response.py
huaweicloudsdkram/v1/model/delete_resource_share_request.py
huaweicloudsdkram/v1/model/delete_resource_share_response.py
huaweicloudsdkram/v1/model/disable_organization_share_request.py
huaweicloudsdkram/v1/model/disable_organization_share_response.py
huaweicloudsdkram/v1/model/disassociate_permission_req_body.py
huaweicloudsdkram/v1/model/disassociate_resource_share_permission_request.py
huaweicloudsdkram/v1/model/disassociate_resource_share_permission_response.py
huaweicloudsdkram/v1/model/disassociate_resource_share_request.py
huaweicloudsdkram/v1/model/disassociate_resource_share_response.py
huaweicloudsdkram/v1/model/distinct_shared_principal.py
huaweicloudsdkram/v1/model/distinct_shared_resource.py
huaweicloudsdkram/v1/model/enable_organization_share_request.py
huaweicloudsdkram-3.1.184.dist-info/METADATA
huaweicloudsdkram-3.1.184.dist-info/WHEEL
huaweicloudsdkram-3.1.184.dist-info/licenses/LICENSE
huaweicloudsdkram-3.1.184.dist-info/RECORD
